{
  "version": "daylight-v17-singularity-field-registry-v0.1",
  "closure_scale": 1000000000000,
  "fields": [
    {
      "id": "claim",
      "name": "ClaimClosure",
      "weight_centi": 100,
      "mode": "claim_score"
    },
    {
      "id": "self",
      "name": "SelfProgress",
      "weight_centi": 125,
      "mode": "self_progress",
      "beta_num": 1,
      "beta_den": 1
    },
    {
      "id": "artifact",
      "name": "HermeticArtifact",
      "weight_centi": 150,
      "mode": "unit_credit",
      "units": [
        {"id": "artifact.solstice_scorecard", "credit": 125, "verifier": "solstice_scorecard_digest"},
        {"id": "artifact.receipt_digest", "credit": 125, "verifier": "solstice_receipt_digest"},
        {"id": "artifact.output_ledger_transition", "credit": 125, "verifier": "solstice_output_ledger"},
        {"id": "artifact.manifest_closure", "credit": 125, "verifier": "solstice_manifest_closure"},
        {"id": "artifact.sha256sums_closure", "credit": 125, "verifier": "solstice_sha256sums_closure"},
        {"id": "artifact.zenith_report_manifest", "credit": 125, "verifier": "zenith_report_manifest"},
        {"id": "artifact.analemma_report_manifest", "credit": 125, "verifier": "analemma_report_manifest"},
        {"id": "artifact.d16_awe_vectors", "credit": 125, "verifier": "evidence_record", "collection": "crypto_vectors", "match_key": "surface", "match_value": "d16_awe_test_vectors"}
      ]
    },
    {
      "id": "replay",
      "name": "ReplayDepth",
      "weight_centi": 125,
      "mode": "unit_credit",
      "units": [
        {"id": "replay.structural", "credit": 200, "verifier": "solstice_verified"},
        {"id": "replay.executable", "credit": 200, "verifier": "zenith_verified"},
        {"id": "replay.replayable", "credit": 200, "verifier": "analemma_verified"},
        {"id": "replay.clean_checkout", "credit": 200, "verifier": "evidence_record", "collection": "replay_evidence", "match_key": "level", "match_value": "clean_checkout"},
        {"id": "replay.independent_environment", "credit": 200, "verifier": "evidence_record", "collection": "replay_evidence", "match_key": "level", "match_value": "independent_environment"}
      ]
    },
    {
      "id": "implementation",
      "name": "MultiImplementation",
      "weight_centi": 150,
      "mode": "unit_credit",
      "units": [
        {"id": "implementation.python_reference", "credit": 200, "verifier": "v17_python_reference"},
        {"id": "implementation.rust_verifier", "credit": 200, "verifier": "zenith_obligation", "obligation": "z4.rust_verifier"},
        {"id": "implementation.third_verifier", "credit": 200, "verifier": "zenith_obligation", "obligation": "z4.third_verifier"},
        {"id": "implementation.intermediate_digest_agreement", "credit": 250, "verifier": "zenith_obligation", "obligation": "z4.intermediate_digest_agreement"},
        {"id": "implementation.negative_divergence_tests", "credit": 150, "verifier": "zenith_obligation", "obligation": "z4.negative_divergence_tests"}
      ]
    },
    {
      "id": "fuzz",
      "name": "AdversarialFuzzing",
      "weight_centi": 125,
      "mode": "unit_credit",
      "units": [
        {"id": "fuzz.parser", "credit": 180, "verifier": "zenith_obligation", "obligation": "z6.parser_fuzz"},
        {"id": "fuzz.artifact", "credit": 170, "verifier": "zenith_obligation", "obligation": "z6.artifact_fuzz"},
        {"id": "fuzz.envelope", "credit": 170, "verifier": "zenith_obligation", "obligation": "z6.envelope_fuzz"},
        {"id": "fuzz.ledger_corpus", "credit": 150, "verifier": "zenith_obligation", "obligation": "z6.ledger_corpus_fuzz"},
        {"id": "fuzz.sanitizer_clean", "credit": 165, "verifier": "zenith_obligation", "obligation": "z6.sanitizer_clean"},
        {"id": "fuzz.crash_triage_closed", "credit": 165, "verifier": "zenith_obligation", "obligation": "z6.crash_triage_closed"}
      ]
    },
    {
      "id": "formal",
      "name": "FormalProof",
      "weight_centi": 150,
      "mode": "unit_credit",
      "units": [
        {"id": "formal.score_monotonicity", "credit": 125, "verifier": "evidence_record", "collection": "formal_proofs", "match_key": "theorem", "match_value": "score_monotonicity"},
        {"id": "formal.manual_score_rejection", "credit": 125, "verifier": "evidence_record", "collection": "formal_proofs", "match_key": "theorem", "match_value": "manual_score_rejection"},
        {"id": "formal.residue_theorem", "credit": 125, "verifier": "evidence_record", "collection": "formal_proofs", "match_key": "theorem", "match_value": "residue_theorem"},
        {"id": "formal.internal_ceiling", "credit": 125, "verifier": "evidence_record", "collection": "formal_proofs", "match_key": "theorem", "match_value": "internal_ceiling"},
        {"id": "formal.perfect_iff_closed", "credit": 125, "verifier": "evidence_record", "collection": "formal_proofs", "match_key": "theorem", "match_value": "perfect_iff_all_obligations_closed"},
        {"id": "formal.no_unsigned_external_credit", "credit": 125, "verifier": "evidence_record", "collection": "formal_proofs", "match_key": "theorem", "match_value": "no_unsigned_external_credit"},
        {"id": "formal.no_score_inflation", "credit": 125, "verifier": "evidence_record", "collection": "formal_proofs", "match_key": "theorem", "match_value": "no_score_inflation"},
        {"id": "formal.fail_closed_open", "credit": 125, "verifier": "evidence_record", "collection": "formal_proofs", "match_key": "theorem", "match_value": "fail_closed_open"}
      ]
    },
    {
      "id": "crypto",
      "name": "CryptoConstruction",
      "weight_centi": 150,
      "mode": "unit_credit",
      "units": [
        {"id": "crypto.hybrid_kem_combiner_vectors", "credit": 112, "verifier": "evidence_record", "collection": "crypto_vectors", "match_key": "surface", "match_value": "hybrid_kem_combiner"},
        {"id": "crypto.key_schedule_vectors", "credit": 111, "verifier": "evidence_record", "collection": "crypto_vectors", "match_key": "surface", "match_value": "key_schedule"},
        {"id": "crypto.aead_positive_vectors", "credit": 111, "verifier": "evidence_record", "collection": "crypto_vectors", "match_key": "surface", "match_value": "aead_positive"},
        {"id": "crypto.aead_negative_vectors", "credit": 111, "verifier": "evidence_record", "collection": "crypto_vectors", "match_key": "surface", "match_value": "aead_negative"},
        {"id": "crypto.signature_vectors", "credit": 111, "verifier": "evidence_record", "collection": "crypto_vectors", "match_key": "surface", "match_value": "signature_verification"},
        {"id": "crypto.policy_bound_auth_tag", "credit": 111, "verifier": "evidence_record", "collection": "crypto_vectors", "match_key": "surface", "match_value": "policy_bound_authorization_tag"},
        {"id": "crypto.nonce_uniqueness_rule", "credit": 111, "verifier": "evidence_record", "collection": "crypto_vectors", "match_key": "surface", "match_value": "nonce_uniqueness_rule"},
        {"id": "crypto.commitment_check", "credit": 111, "verifier": "evidence_record", "collection": "crypto_vectors", "match_key": "surface", "match_value": "commitment_check"},
        {"id": "crypto.fail_closed_mutation_corpus", "credit": 111, "verifier": "evidence_record", "collection": "crypto_vectors", "match_key": "surface", "match_value": "fail_closed_mutation_corpus"}
      ]
    },
    {
      "id": "falsification",
      "name": "PublicFalsification",
      "weight_centi": 125,
      "mode": "unit_credit",
      "units": [
        {"id": "falsification.challenge_spec", "credit": 170, "verifier": "zenith_obligation", "obligation": "z9.challenge_spec"},
        {"id": "falsification.break_taxonomy", "credit": 165, "verifier": "zenith_obligation", "obligation": "z9.break_class_taxonomy"},
        {"id": "falsification.public_reproducer_rule", "credit": 170, "verifier": "zenith_obligation", "obligation": "z9.public_reproducer_rule"},
        {"id": "falsification.adjudication_signature", "credit": 165, "verifier": "zenith_obligation", "obligation": "z9.adjudication_signature"},
        {"id": "falsification.open_break_ledger", "credit": 165, "verifier": "zenith_obligation", "obligation": "z9.open_break_ledger"},
        {"id": "falsification.zero_critical_open", "credit": 165, "verifier": "zenith_obligation", "obligation": "z9.zero_critical_open"}
      ]
    },
    {
      "id": "boundary",
      "name": "BoundaryDiscipline",
      "weight_centi": 150,
      "mode": "unit_credit",
      "units": [
        {"id": "boundary.production_authority_gate", "credit": 175, "verifier": "evidence_record", "collection": "boundary_evidence", "match_key": "rule", "match_value": "production_authority_gate"},
        {"id": "boundary.runtime_containment_gate", "credit": 175, "verifier": "evidence_record", "collection": "boundary_evidence", "match_key": "rule", "match_value": "runtime_containment_gate"},
        {"id": "boundary.pq_claim_gate", "credit": 175, "verifier": "evidence_record", "collection": "boundary_evidence", "match_key": "rule", "match_value": "pq_claim_gate"},
        {"id": "boundary.fixture_quarantine", "credit": 175, "verifier": "evidence_record", "collection": "boundary_evidence", "match_key": "rule", "match_value": "fixture_quarantine"},
        {"id": "boundary.nonclaim_enforcement", "credit": 175, "verifier": "evidence_record", "collection": "boundary_evidence", "match_key": "rule", "match_value": "nonclaim_enforcement"},
        {"id": "boundary.unsupported_fail_closed", "credit": 125, "verifier": "evidence_record", "collection": "boundary_evidence", "match_key": "rule", "match_value": "unsupported_fail_closed"}
      ]
    }
  ]
}
